LICENSE
MANIFEST.in
README.rst
setup.py
django_misaka/__init__.py
django_misaka.egg-info/.DS_Store
django_misaka.egg-info/PKG-INFO
django_misaka.egg-info/SOURCES.txt
django_misaka.egg-info/dependency_links.txt
django_misaka.egg-info/pbr.json
django_misaka.egg-info/requires.txt
django_misaka.egg-info/top_level.txt
django_misaka/templatetags/.DS_Store
django_misaka/templatetags/__init__.py
django_misaka/templatetags/markdown.py